glitterin/__init__.py
glitterin/data.py
glitterin/dust.py
glitterin/network.py
glitterin/toolkit.py
glitterin/user.py
glitterin-1.0.0.dist-info/licenses/LICENSE
glitterin-1.0.0.dist-info/METADATA
glitterin-1.0.0.dist-info/WHEEL
glitterin-1.0.0.dist-info/top_level.txt
glitterin-1.0.0.dist-info/RECORD
