Metadata-Version: 2.4
Name: glitterin
Version: 1.0.0
Summary: User interface for using pytorch neural network trained on scattering of irregular grains through ADDA.
Author-email: Zhe-Yu Daniel Lin <dlin@nrao.edu>
License: MIT License
Project-URL: Homepage, https://github.com/zheyudaniellin/glitterin
Project-URL: Bug Reports, https://github.com/zheyudaniellin/glitterin/issues
Project-URL: Source, https://github.com/zheyudaniellin/glitterin
Project-URL: Documentation, https://github.com/zheyudaniellin/glitterin#readme
Keywords: astronomy,neural-networks,pytorch,machine-learning
Requires-Python: >=3.10
License-File: LICENSE
Requires-Dist: numpy>=2.2.4
Requires-Dist: h5py>=3.13.0
Requires-Dist: torch>=2.6.0
Requires-Dist: scikit-learn>=1.6.1
Dynamic: license-file
